tactis/__init__.py
tactis/gluon/__init__.py
tactis/gluon/backtest.py
tactis/gluon/dataset.py
tactis/gluon/estimator.py
tactis/gluon/metrics.py
tactis/gluon/network.py
tactis/gluon/plots.py
tactis/gluon/trainer.py
tactis/gluon/utils.py
tactis/model/__init__.py
tactis/model/decoder.py
tactis/model/encoder.py
tactis/model/flow.py
tactis/model/marginal.py
tactis/model/tactis.py
tactis/model/utils.py
tactis-0.1.3.dist-info/LICENSE
tactis-0.1.3.dist-info/METADATA
tactis-0.1.3.dist-info/NOTICE
tactis-0.1.3.dist-info/WHEEL
tactis-0.1.3.dist-info/top_level.txt
tactis-0.1.3.dist-info/RECORD
