Metadata-Version: 2.1
Name: tactis
Version: 0.1.3
Summary: Transformer-Attentional Copulas for Multivariate Time Series
Home-page: https://github.com/ServiceNow/tactis/tree/tactis-2
Author: Arjun Ashok, Étienne Marcotte, Valentina Zantedeschi, Nicolas Chapados, Alexandre Drouin
License-File: LICENSE
License-File: NOTICE
Requires-Dist: matplotlib (>=3.4.3)
Requires-Dist: numpy (>=1.23.5)
Requires-Dist: pandas (>=1.5.3)
Requires-Dist: seaborn (>=0.13.0)
Requires-Dist: torch (>=1.13.1)
Provides-Extra: research
Requires-Dist: gluonts (==0.9.6) ; extra == 'research'
Requires-Dist: pytorchts (==0.6.0) ; extra == 'research'
